setup.py
lsw_distributions/Binomialdistribution.py
lsw_distributions/Gaussiandistribution.py
lsw_distributions/Generaldistribution.py
lsw_distributions/__init__.py
lsw_distributions.egg-info/PKG-INFO
lsw_distributions.egg-info/SOURCES.txt
lsw_distributions.egg-info/dependency_links.txt
lsw_distributions.egg-info/not-zip-safe
lsw_distributions.egg-info/top_level.txt