Metadata-Version: 1.0
Name: lsw-distributions
Version: 0.1
Summary: Gaussian and Binomial distributions
Home-page: UNKNOWN
Author: Steve Wasik
Author-email: steven.l.wasik@gmail.com
License: UNKNOWN
Platform: UNKNOWN
